vc_web_email/__init__.py
vc_web_email/client.py
vc_web_email/config.py
vc_web_email/exceptions.py
vc_web_email/message.py
vc_web_email/py.typed
vc_web_email/response.py
vc_web_email/providers/__init__.py
vc_web_email/providers/aws_ses.py
vc_web_email/providers/base.py
vc_web_email/providers/gmail.py
vc_web_email/providers/mailgun.py
vc_web_email/providers/outlook.py
vc_web_email/providers/sendgrid.py
vc_web_email/providers/smtp.py
vc_web_email/utils/__init__.py
vc_web_email/utils/logger.py
vc_web_email/utils/validator.py
vc_web_email-1.0.0.dist-info/LICENSE
vc_web_email-1.0.0.dist-info/METADATA
vc_web_email-1.0.0.dist-info/WHEEL
vc_web_email-1.0.0.dist-info/top_level.txt
vc_web_email-1.0.0.dist-info/RECORD
