Metadata-Version: 2.1
Name: vc-web-email
Version: 1.0.0
Summary: A unified email library for VentureCube organization - supports SMTP, Gmail, SendGrid, AWS SES, and Mailgun
Author-email: VentureCube <support@venturecube.com>
Maintainer-email: VentureCube <support@venturecube.com>
Project-URL: Homepage, https://github.com/venturecube/vc-web-email
Project-URL: Documentation, https://github.com/venturecube/vc-web-email#readme
Project-URL: Repository, https://github.com/venturecube/vc-web-email.git
Project-URL: Issues, https://github.com/venturecube/vc-web-email/issues
Keywords: email,smtp,gmail,sendgrid,aws-ses,mailgun,email-client,venturecube
Classifier: Development Status :: 5 - Production/Stable
Classifier: Intended Audience :: Developers
Classifier: License :: OSI Approved :: MIT License
Classifier: Operating System :: OS Independent
Classifier: Programming Language :: Python :: 3
Classifier: Programming Language :: Python :: 3.8
Classifier: Programming Language :: Python :: 3.9
Classifier: Programming Language :: Python :: 3.10
Classifier: Programming Language :: Python :: 3.11
Classifier: Programming Language :: Python :: 3.12
Classifier: Topic :: Communications :: Email
Classifier: Topic :: Software Development :: Libraries :: Python Modules
Classifier: Typing :: Typed
Requires-Python: >=3.8
License-File: LICENSE
Requires-Dist: PyYAML>=6.0
Provides-Extra: all
Requires-Dist: sendgrid>=6.0; extra == "all"
Requires-Dist: boto3>=1.26; extra == "all"
Provides-Extra: aws
Requires-Dist: boto3>=1.26; extra == "aws"
Provides-Extra: dev
Requires-Dist: pytest>=7.0; extra == "dev"
Requires-Dist: pytest-cov>=4.0; extra == "dev"
Requires-Dist: black>=23.0; extra == "dev"
Requires-Dist: flake8>=6.0; extra == "dev"
Requires-Dist: mypy>=1.0; extra == "dev"
Requires-Dist: isort>=5.12; extra == "dev"
Requires-Dist: pre-commit>=3.0; extra == "dev"
Requires-Dist: types-PyYAML>=6.0; extra == "dev"
Provides-Extra: mailgun
Provides-Extra: sendgrid
Requires-Dist: sendgrid>=6.0; extra == "sendgrid"
